minmodkg/__init__.py
minmodkg/api.py
minmodkg/entity_linking.py
minmodkg/fuseki_deployment.py
minmodkg/grade_tonnage_model.py
minmodkg/misc.py
minmodkg/transformations.py
ta2_minmod_kg-1.1.0.dist-info/LICENSE
ta2_minmod_kg-1.1.0.dist-info/METADATA
ta2_minmod_kg-1.1.0.dist-info/WHEEL
ta2_minmod_kg-1.1.0.dist-info/RECORD
